tooltils/__init__.py
tooltils/__main__.py
tooltils/_utils.py
tooltils/errors.py
tooltils/info.py
tooltils/os.py
tooltils/requests/__init__.py
tooltils/requests/_helpers.py
tooltils/requests/urllib.py
tooltils-1.8.0.dist-info/LICENSE
tooltils-1.8.0.dist-info/METADATA
tooltils-1.8.0.dist-info/WHEEL
tooltils-1.8.0.dist-info/top_level.txt
tooltils-1.8.0.dist-info/RECORD
