Metadata-Version: 2.1
Name: tooltils
Version: 1.8.0
Summary: A lightweight python utility package built on the standard library
Author: feetbots
Author-email: feetbots <pheetbots@gmail.com>
License: MIT License
Project-URL: Homepage, https://github.com/feetbots/tooltils
Project-URL: Issues, https://github.com/feetbots/tooltils/issues
Classifier: Programming Language :: Python :: 3
Classifier: Programming Language :: Python :: 3.7
Classifier: Programming Language :: Python :: 3.8
Classifier: Programming Language :: Python :: 3.9
Classifier: Programming Language :: Python :: 3.10
Classifier: Programming Language :: Python :: 3.11
Classifier: Programming Language :: Python :: 3.12
Classifier: License :: OSI Approved :: MIT License
Classifier: Operating System :: OS Independent
Requires-Python: >=3.7
License-File: LICENSE
